priority_summary_verify/__init__.py
priority_summary_verify/priority.py
priority_summary_verify/summary.py
priority_summary_verify/verify.py
my_library_package-0.1.dist-info/METADATA
my_library_package-0.1.dist-info/WHEEL
my_library_package-0.1.dist-info/top_level.txt
my_library_package-0.1.dist-info/RECORD
