Metadata-Version: 2.1
Name: my_library_package
Version: 0.1
Summary: A collection of independent libraries for diff functionalities
Home-page: https://example.com/library
Author: Maitreyee
